mlops_batch_prediction/__init__.py
mlops_batch_prediction/batch.py
mlops_batch_prediction/data.py
mlops_batch_prediction/monitoring.py
mlops_batch_prediction/settings.py
mlops_batch_prediction/transformers.py
mlops_batch_prediction/utils.py
mlops_batch_prediction_pipeline-0.10.0.dist-info/METADATA
mlops_batch_prediction_pipeline-0.10.0.dist-info/WHEEL
mlops_batch_prediction_pipeline-0.10.0.dist-info/RECORD
