Metadata-Version: 2.1
Name: mlops_batch_prediction_pipeline
Version: 0.10.0
Summary: 
Author: CryLake
Author-email: minhchauss123456@gmail.com
Requires-Python: >=3.10,<3.11
Classifier: Programming Language :: Python :: 3
Classifier: Programming Language :: Python :: 3.10
Requires-Dist: category-encoders (>=2.6.0,<3.0.0)
Requires-Dist: fire (>=0.5.0,<0.6.0)
Requires-Dist: google-cloud-storage (>=2.7.0,<3.0.0)
Requires-Dist: hopsworks (==3.2.0)
Requires-Dist: lightgbm (>=3.3.5,<4.0.0)
Requires-Dist: mlops_training_pipeline (==0.9.0)
Requires-Dist: python-dotenv (>=1.0.0,<2.0.0)
Requires-Dist: sktime (>=0.16.1,<0.17.0)
